piny/__init__.py
piny/cli.py
piny/errors.py
piny/loaders.py
piny/matchers.py
piny/validators.py
piny-1.1.0.dist-info/LICENSE
piny-1.1.0.dist-info/METADATA
piny-1.1.0.dist-info/WHEEL
piny-1.1.0.dist-info/entry_points.txt
piny-1.1.0.dist-info/top_level.txt
piny-1.1.0.dist-info/RECORD
