Metadata-Version: 2.1
Name: piny
Version: 1.1.0
Summary: Load YAML configs with environment variables interpolation
Author-email: Vitaly Samigullin <vrs@pilosus.org>
License: MIT
Project-URL: Source code, https://github.com/pilosus/piny/
Project-URL: Issue tracker, https://github.com/pilosus/piny/issues
Project-URL: Documentation, https://piny.readthedocs.io/en/latest/
Classifier: Programming Language :: Python :: 3
Classifier: Intended Audience :: Developers
Classifier: Intended Audience :: Information Technology
Classifier: Intended Audience :: System Administrators
Classifier: License :: OSI Approved :: MIT License
Classifier: Operating System :: Unix
Classifier: Operating System :: POSIX :: Linux
Classifier: Environment :: Console
Classifier: Environment :: MacOS X
Classifier: Topic :: Software Development :: Libraries :: Python Modules
Classifier: Topic :: Internet
Requires-Python: >=3.7
License-File: LICENSE
Requires-Dist: PyYAML <7,>=6
Requires-Dist: Click <9,>=8
Provides-Extra: marshmallow
Requires-Dist: marshmallow >=3 ; extra == 'marshmallow'
Provides-Extra: pydantic
Requires-Dist: pydantic >=0.28 ; extra == 'pydantic'
Provides-Extra: trafaret
Requires-Dist: trafaret >=1.2.0 ; extra == 'trafaret'
